simplebardapi/__init__.py
simplebardapi-1.0.1.dist-info/LICENSE
simplebardapi-1.0.1.dist-info/METADATA
simplebardapi-1.0.1.dist-info/WHEEL
simplebardapi-1.0.1.dist-info/top_level.txt
simplebardapi-1.0.1.dist-info/RECORD
