Metadata-Version: 2.1
Name: simplebardapi
Version: 1.0.1
Summary: A simpler and faster version of BardAPI.
Home-page: https://github.com/Ruu3f/simplebardapi
Author: Ruu3f
License: GPLv3
Project-URL: Source, https://github.com/Ruu3f/simplebardapi
Keywords: artificial-intelligence,google-bard-api,google-bard,bard-api,google,bard,ai
Classifier: Development Status :: 5 - Production/Stable
Classifier: Intended Audience :: Developers
Classifier: License :: OSI Approved :: GNU General Public License v2 (GPLv2)
Classifier: Natural Language :: English
Classifier: Programming Language :: Python :: 3
Classifier: Programming Language :: Python :: 3.6
Classifier: Programming Language :: Python :: 3.7
Classifier: Programming Language :: Python :: 3.8
Classifier: Programming Language :: Python :: 3.9
Classifier: Programming Language :: Python :: 3.10
Classifier: Programming Language :: Python :: 3.11
Classifier: Programming Language :: Python :: Implementation :: CPython
Classifier: Programming Language :: Python :: Implementation :: PyPy
Requires-Python: >=3.6
License-File: LICENSE
Requires-Dist: requests
